[
    {
        "name": "Tasnim",
        "email": "tasnim@gmail.com",
        "password": "1234",
        "comment": "my file!!!!!",
        "gender": "Female",
        "hobby": "Travelling,Dancing",
        "file_path": "File\/Blue_butterfly-wallpaper-10553641.jpg"
    },
    {
        "Name": "tasnim bintey khairul",
        "Email": "tasnim13aiub@gmail.com",
        "Password": "1234",
        "Comment": "ttta",
        "Gender": "Female",
        "Hobby": ",Travelling",
        "File_Path": "File\/Blue_butterfly-wallpaper-10553641.jpg"
    },
    {
        "Name": "tasnim bintey khairul",
        "Email": "tasnim13aiub@gmail.com",
        "Password": "1234",
        "Comment": "ttta",
        "Gender": "Female",
        "Hobby": ",Travelling",
        "File_Path": "File\/Blue_butterfly-wallpaper-10553641.jpg"
    },
    {
        "Name": "tasnim bintey khairul",
        "Email": "tasnim13aiub@gmail.com",
        "Password": "1234",
        "Comment": "ttta",
        "Gender": "Female",
        "Hobby": ",Travelling",
        "File_Path": "File\/Blue_butterfly-wallpaper-10553641.jpg"
    },
    {
        "Name": "tasnim bintey khairul",
        "Email": "tasnimkhairul07@gmail.com",
        "Password": "1234",
        "Comment": "nn",
        "Gender": "Female",
        "Hobby": ",Travelling",
        "File_Path": "File\/Blue_butterfly-wallpaper-10553641.jpg"
    },
    {
        "Name": "tasnim bintey khairul",
        "Email": "tasnimkhairul07@gmail.com",
        "Password": "1234",
        "Comment": "nn",
        "Gender": "Female",
        "Hobby": ",Travelling",
        "File_Path": "File\/Blue_butterfly-wallpaper-10553641.jpg"
    },
    {
        "Name": "tasnim bintey khairul",
        "Email": "tasnimkhairul07@gmail.com",
        "Password": "1234",
        "Comment": "nn",
        "Gender": "Female",
        "Hobby": ",Travelling",
        "File_Path": "File\/Blue_butterfly-wallpaper-10553641.jpg"
    },
    {
        "Name": "tasnim bintey khairul",
        "Email": "tasnimkhairul07@gmail.com",
        "Password": "1234",
        "Comment": "nn",
        "Gender": "Female",
        "Hobby": ",Travelling",
        "File_Path": "File\/Blue_butterfly-wallpaper-10553641.jpg"
    },
    {
        "Name": "tasnim bintey khairul",
        "Email": "tasnimkhairul07@gmail.com",
        "Password": "1234",
        "Comment": "nn",
        "Gender": "Female",
        "Hobby": ",Travelling",
        "File_Path": "File\/Blue_butterfly-wallpaper-10553641.jpg"
    },
    {
        "Name": "tasnim bintey khairul",
        "Email": "tasnimkhairul07@gmail.com",
        "Password": "1234",
        "Comment": "nn",
        "Gender": "Female",
        "Hobby": ",Travelling",
        "File_Path": "File\/Blue_butterfly-wallpaper-10553641.jpg"
    },
    {
        "Name": "tasnim bintey khairul",
        "Email": "tasnimkhairul07@gmail.com",
        "Password": "1234",
        "Comment": "nn",
        "Gender": "Female",
        "Hobby": ",Travelling",
        "File_Path": "File\/Blue_butterfly-wallpaper-10553641.jpg"
    },
    {
        "Name": "tasnim bintey khairul",
        "Email": "tasnimkhairul07@gmail.com",
        "Password": "1234",
        "Comment": "nn",
        "Gender": "Female",
        "Hobby": ",Travelling",
        "File_Path": "File\/Blue_butterfly-wallpaper-10553641.jpg"
    },
    {
        "Name": "tasnim bintey khairul",
        "Email": "tasnimkhairul07@gmail.com",
        "Password": "1234",
        "Comment": "nn",
        "Gender": "Female",
        "Hobby": ",Travelling",
        "File_Path": "File\/Blue_butterfly-wallpaper-10553641.jpg"
    },
    {
        "Name": "tasnim bintey khairul",
        "Email": "tasnimkhairul07@gmail.com",
        "Password": "1234",
        "Comment": "nn",
        "Gender": "Female",
        "Hobby": ",Travelling",
        "File_Path": "File\/Blue_butterfly-wallpaper-10553641.jpg"
    },
    {
        "Name": "tasnim bintey khairul",
        "Email": "tasnimkhairul07@gmail.com",
        "Password": "",
        "Comment": "nn",
        "Gender": "Female",
        "Hobby": ",Travelling",
        "File_Path": "File\/"
    },
    {
        "Name": "tasnim bintey khairul",
        "Email": "tasnimkhairul07@gmail.com",
        "Password": "1234",
        "Comment": "nn",
        "Gender": "Female",
        "Hobby": ",Travelling",
        "File_Path": "File\/Blue_butterfly-wallpaper-10553641.jpg"
    }
]